propheto/__init__.py
propheto/__main__.py
propheto/app.py
propheto/deployments/__init__.py
propheto/deployments/aws/__init__.py
propheto/deployments/aws/api_gateway.py
propheto/deployments/aws/aws_lambda.py
propheto/deployments/aws/boto_session.py
propheto/deployments/aws/cloudformation.py
propheto/deployments/aws/cloudwatch.py
propheto/deployments/aws/codebuild.py
propheto/deployments/aws/ecr.py
propheto/deployments/aws/iam.py
propheto/deployments/aws/s3.py
propheto/deployments/azure/__init__.py
propheto/deployments/gcp/__init__.py
propheto/model_frameworks/__init__.py
propheto/model_frameworks/pytorch.py
propheto/model_frameworks/registry.py
propheto/model_frameworks/sklearn.py
propheto/model_frameworks/tensorflow.py
propheto/package/__init__.py
propheto/package/environment.py
propheto/package/introspect.py
propheto/package/models.py
propheto/package/service.py
propheto/package/templates/api/main.py
propheto/package/templates/api/v1/__init__.py
propheto/package/templates/api/v1/endpoints/__init__.py
propheto/package/templates/api/v1/endpoints/alerts.py
propheto/package/templates/api/v1/endpoints/logs.py
propheto/package/templates/api/v1/endpoints/model.py
propheto/package/templates/api/v1/routers.py
propheto/package/zip.py
propheto/project/__init__.py
propheto/project/api.py
propheto/project/configuration/__init__.py
propheto/project/configuration/configuration.py
propheto/project/configuration/iteration.py
propheto/project/configuration/local_configuration.py
propheto/project/configuration/project_configuration.py
propheto/project/configuration/remote_configuration.py
propheto/project/configuration/resource.py
propheto/tracking/__init__.py
propheto/tracking/alert.py
propheto/tracking/log.py
propheto/tracking/monitor.py
propheto/utilities.py
propheto-0.1.10.dist-info/LICENSE
propheto-0.1.10.dist-info/WHEEL
propheto-0.1.10.dist-info/METADATA
propheto-0.1.10.dist-info/RECORD
